mobile_balance/__init__.py
mobile_balance/exceptions.py
mobile_balance/main.py
mobile_balance/megafon.py
mobile_balance/megafon_corp.py
mobile_balance/mts.py
mobile_balance/tele2.py
mobile_balance/ttk.py
mobile_balance/utils.py
mobile_balance-0.8.0.dist-info/DESCRIPTION.rst
mobile_balance-0.8.0.dist-info/METADATA
mobile_balance-0.8.0.dist-info/RECORD
mobile_balance-0.8.0.dist-info/WHEEL
mobile_balance-0.8.0.dist-info/entry_points.txt
mobile_balance-0.8.0.dist-info/metadata.json
mobile_balance-0.8.0.dist-info/top_level.txt
mobile_balance-0.8.0.dist-info/zip-safe
