Metadata-Version: 2.0
Name: mobile-balance
Version: 0.8.0
Summary: A set of utilities to retrive a balance from some Russian mobile operators.
Home-page: https://github.com/svetlyak40wt/mobile-balance
Author: Alexander Artemenko
Author-email: svetlyak.40wt@gmail.com
License: BSD
Keywords: mobile,balance,utility
Platform: UNKNOWN
Classifier: Development Status :: 3 - Alpha
Classifier: Environment :: Console
Classifier: Intended Audience :: Developers
Classifier: Natural Language :: English
Classifier: License :: OSI Approved :: BSD License
Classifier: Programming Language :: Python
Classifier: Programming Language :: Python :: 2
Classifier: Programming Language :: Python :: 2.7
Requires-Dist: requests
Requires-Dist: docopt (<0.7.0)
Requires-Dist: pyopenssl
Requires-Dist: ndg-httpsclient
Requires-Dist: pyasn1
